py_dict_repr/__about__.py
py_dict_repr/__init__.py
py_dict_repr/py_dict_repr.py
py_dict_repr/version.py
py_dict_repr-0.2.0b2.dist-info/LICENSE
py_dict_repr-0.2.0b2.dist-info/METADATA
py_dict_repr-0.2.0b2.dist-info/WHEEL
py_dict_repr-0.2.0b2.dist-info/top_level.txt
py_dict_repr-0.2.0b2.dist-info/RECORD
