Metadata-Version: 2.1
Name: py-dict-repr
Version: 0.2.0b2
Summary: An abstract class to enable abitrary classes to define their own dictionary representation.
Home-page: https://github.com/zcutlip/py-dict-repr
Author: Zachary Cutlip
Author-email: uid000@gmail.com
License: MIT
Platform: UNKNOWN
Requires-Python: >=3.7
License-File: LICENSE
